lvldb.py
lvldb-0.1.2.dist-info/LICENSE
lvldb-0.1.2.dist-info/METADATA
lvldb-0.1.2.dist-info/WHEEL
lvldb-0.1.2.dist-info/top_level.txt
lvldb-0.1.2.dist-info/RECORD
