Metadata-Version: 2.1
Name: lvldb
Version: 0.1.2
Summary: Python bindings for LevelDB. Python 2-3 compatible
Home-page: https://github.com/jtolio/leveldb-py
Author: JT Olds
Author-email: jt@spacemonkey.com
Keywords: Python,LevelDB
License-File: LICENSE
